{
    "image_name": "1.mp4/404.jpg",
    "body_info": [
        {
            "box": [
                238,
                62,
                1692,
                1023,
                1
            ],
            "action_cls": "walk",
            "img_action_cls": [
                "stand",
                "smoke"
            ],
            "keypoints": [],
            "adjacent_keypoints": []
        }
    ],
    "face_info": [
        {
            "key_points": [
                [
                    693,
                    269
                ],
                [
                    686,
                    355
                ],
                [
                    693,
                    444
                ],
                [
                    708,
                    529
                ],
                [
                    732,
                    610
                ],
                [
                    767,
                    676
                ],
                [
                    810,
                    726
                ],
                [
                    858,
                    765
                ],
                [
                    921,
                    780
                ],
                [
                    991,
                    773
                ],
                [
                    1055,
                    743
                ],
                [
                    1122,
                    709
                ],
                [
                    1182,
                    660
                ],
                [
                    1238,
                    595
                ],
                [
                    1276,
                    514
                ],
                [
                    1300,
                    424
                ],
                [
                    1313,
                    331
                ],
                [
                    727,
                    144
                ],
                [
                    777,
                    113
                ],
                [
                    835,
                    108
                ],
                [
                    892,
                    120
                ],
                [
                    939,
                    154
                ],
                [
                    1040,
                    156
                ],
                [
                    1091,
                    135
                ],
                [
                    1148,
                    133
                ],
                [
                    1201,
                    145
                ],
                [
                    1245,
                    186
                ],
                [
                    977,
                    235
                ],
                [
                    970,
                    311
                ],
                [
                    962,
                    386
                ],
                [
                    955,
                    461
                ],
                [
                    887,
                    486
                ],
                [
                    917,
                    506
                ],
                [
                    951,
                    519
                ],
                [
                    988,
                    512
                ],
                [
                    1023,
                    498
                ],
                [
                    778,
                    234
                ],
                [
                    814,
                    201
                ],
                [
                    861,
                    202
                ],
                [
                    898,
                    247
                ],
                [
                    856,
                    258
                ],
                [
                    810,
                    256
                ],
                [
                    1073,
                    257
                ],
                [
                    1115,
                    217
                ],
                [
                    1162,
                    219
                ],
                [
                    1192,
                    257
                ],
                [
                    1160,
                    274
                ],
                [
                    1113,
                    271
                ],
                [
                    857,
                    610
                ],
                [
                    890,
                    585
                ],
                [
                    926,
                    572
                ],
                [
                    945,
                    582
                ],
                [
                    965,
                    577
                ],
                [
                    998,
                    599
                ],
                [
                    1033,
                    630
                ],
                [
                    988,
                    645
                ],
                [
                    954,
                    655
                ],
                [
                    933,
                    654
                ],
                [
                    912,
                    650
                ],
                [
                    884,
                    633
                ],
                [
                    875,
                    607
                ],
                [
                    922,
                    600
                ],
                [
                    942,
                    606
                ],
                [
                    962,
                    607
                ],
                [
                    1015,
                    625
                ],
                [
                    958,
                    607
                ],
                [
                    937,
                    607
                ],
                [
                    919,
                    601
                ]
            ],
            "face_coordinate": [
                632,
                33,
                1292,
                738
            ],
            "expression": "nature",
            "attention_score": 0.9172727272727272
        }
    ]
}