{
    "image_name": "wushu.mp4/1056.jpg",
    "body_info": [
        {
            "box": [
                666,
                282,
                1474,
                1018,
                1
            ],
            "action_cls": "clap",
            "img_action_cls": [
                "stand",
                "phone"
            ],
            "keypoints": [
                [
                    215.5095447345024,
                    156.682995955365,
                    9.83690321445465
                ],
                [
                    226.1566926763299,
                    127.90739069703153,
                    9.07255232334137
                ],
                [
                    186.57823575956843,
                    144.9270906487184,
                    7.6457661390304565
                ],
                [
                    243.62427403715517,
                    103.54180759134901,
                    8.289636373519897
                ],
                [
                    300.9670945975962,
                    352.0115382118173,
                    8.651866912841797
                ]
            ],
            "adjacent_keypoints": []
        }
    ],
    "face_info": [
        {
            "key_points": [
                [
                    815,
                    361
                ],
                [
                    814,
                    379
                ],
                [
                    816,
                    396
                ],
                [
                    819,
                    412
                ],
                [
                    825,
                    427
                ],
                [
                    833,
                    440
                ],
                [
                    844,
                    452
                ],
                [
                    856,
                    460
                ],
                [
                    868,
                    461
                ],
                [
                    881,
                    458
                ],
                [
                    895,
                    449
                ],
                [
                    906,
                    437
                ],
                [
                    914,
                    422
                ],
                [
                    919,
                    406
                ],
                [
                    920,
                    388
                ],
                [
                    921,
                    372
                ],
                [
                    921,
                    355
                ],
                [
                    819,
                    350
                ],
                [
                    826,
                    342
                ],
                [
                    836,
                    340
                ],
                [
                    846,
                    339
                ],
                [
                    854,
                    343
                ],
                [
                    873,
                    338
                ],
                [
                    883,
                    332
                ],
                [
                    893,
                    331
                ],
                [
                    902,
                    333
                ],
                [
                    909,
                    339
                ],
                [
                    863,
                    355
                ],
                [
                    863,
                    370
                ],
                [
                    863,
                    384
                ],
                [
                    864,
                    398
                ],
                [
                    853,
                    402
                ],
                [
                    859,
                    405
                ],
                [
                    865,
                    407
                ],
                [
                    871,
                    403
                ],
                [
                    875,
                    400
                ],
                [
                    829,
                    361
                ],
                [
                    835,
                    356
                ],
                [
                    843,
                    356
                ],
                [
                    849,
                    360
                ],
                [
                    843,
                    363
                ],
                [
                    836,
                    363
                ],
                [
                    880,
                    356
                ],
                [
                    887,
                    350
                ],
                [
                    894,
                    349
                ],
                [
                    899,
                    353
                ],
                [
                    895,
                    356
                ],
                [
                    888,
                    357
                ],
                [
                    841,
                    420
                ],
                [
                    850,
                    417
                ],
                [
                    859,
                    417
                ],
                [
                    865,
                    419
                ],
                [
                    872,
                    416
                ],
                [
                    882,
                    415
                ],
                [
                    894,
                    412
                ],
                [
                    884,
                    422
                ],
                [
                    873,
                    427
                ],
                [
                    866,
                    429
                ],
                [
                    860,
                    430
                ],
                [
                    851,
                    427
                ],
                [
                    845,
                    420
                ],
                [
                    860,
                    423
                ],
                [
                    865,
                    423
                ],
                [
                    872,
                    421
                ],
                [
                    891,
                    414
                ],
                [
                    872,
                    420
                ],
                [
                    866,
                    423
                ],
                [
                    860,
                    422
                ]
            ],
            "face_coordinate": [
                789,
                316,
                920,
                465
            ],
            "expression": "nature",
            "attention_score": 0.22727272727272727
        }
    ]
}