{
    "image_name": "wushu.mp4/1094.jpg",
    "body_info": [
        {
            "box": [
                707,
                255,
                1434,
                1019,
                1
            ],
            "action_cls": "clap",
            "img_action_cls": [
                "climb",
                "phone"
            ],
            "keypoints": [],
            "adjacent_keypoints": []
        }
    ],
    "face_info": [
        {
            "key_points": [
                [
                    791,
                    306
                ],
                [
                    789,
                    326
                ],
                [
                    789,
                    347
                ],
                [
                    789,
                    368
                ],
                [
                    793,
                    388
                ],
                [
                    801,
                    406
                ],
                [
                    810,
                    420
                ],
                [
                    820,
                    433
                ],
                [
                    836,
                    441
                ],
                [
                    853,
                    441
                ],
                [
                    869,
                    434
                ],
                [
                    883,
                    421
                ],
                [
                    895,
                    405
                ],
                [
                    905,
                    384
                ],
                [
                    910,
                    363
                ],
                [
                    914,
                    340
                ],
                [
                    916,
                    317
                ],
                [
                    796,
                    292
                ],
                [
                    802,
                    281
                ],
                [
                    812,
                    279
                ],
                [
                    823,
                    282
                ],
                [
                    834,
                    289
                ],
                [
                    857,
                    293
                ],
                [
                    870,
                    287
                ],
                [
                    884,
                    287
                ],
                [
                    895,
                    294
                ],
                [
                    902,
                    307
                ],
                [
                    843,
                    307
                ],
                [
                    841,
                    321
                ],
                [
                    839,
                    333
                ],
                [
                    837,
                    347
                ],
                [
                    825,
                    354
                ],
                [
                    831,
                    359
                ],
                [
                    838,
                    362
                ],
                [
                    846,
                    361
                ],
                [
                    853,
                    359
                ],
                [
                    807,
                    304
                ],
                [
                    813,
                    300
                ],
                [
                    820,
                    301
                ],
                [
                    827,
                    307
                ],
                [
                    820,
                    307
                ],
                [
                    812,
                    307
                ],
                [
                    864,
                    313
                ],
                [
                    872,
                    309
                ],
                [
                    881,
                    310
                ],
                [
                    887,
                    316
                ],
                [
                    880,
                    318
                ],
                [
                    872,
                    316
                ],
                [
                    818,
                    379
                ],
                [
                    825,
                    374
                ],
                [
                    833,
                    374
                ],
                [
                    838,
                    377
                ],
                [
                    844,
                    377
                ],
                [
                    856,
                    381
                ],
                [
                    866,
                    390
                ],
                [
                    855,
                    403
                ],
                [
                    843,
                    406
                ],
                [
                    836,
                    404
                ],
                [
                    830,
                    401
                ],
                [
                    824,
                    392
                ],
                [
                    822,
                    380
                ],
                [
                    832,
                    379
                ],
                [
                    837,
                    381
                ],
                [
                    844,
                    383
                ],
                [
                    862,
                    389
                ],
                [
                    843,
                    396
                ],
                [
                    837,
                    395
                ],
                [
                    831,
                    391
                ]
            ],
            "face_coordinate": [
                779,
                272,
                902,
                429
            ],
            "expression": "amazing",
            "attention_score": 0.7625
        }
    ]
}