{
    "image_name": "wushu.mp4/310.jpg",
    "body_info": [
        {
            "box": [
                893,
                230,
                1209,
                1037,
                1
            ],
            "action_cls": "walk",
            "img_action_cls": [
                "climb",
                "phone"
            ],
            "keypoints": [
                [
                    140.0539716564241,
                    52.34403375204136,
                    9.962820410728455
                ],
                [
                    157.83215867339587,
                    33.363326997792676,
                    9.701055884361267
                ],
                [
                    120.19594507061068,
                    33.079261652985764,
                    9.987972974777222
                ],
                [
                    180.96741664761402,
                    50.519634801350286,
                    8.005954623222351
                ],
                [
                    89.44548542460457,
                    52.50807275843531,
                    8.402349948883057
                ],
                [
                    88.29999811141218,
                    638.7045369648308,
                    4.185719192028046
                ],
                [
                    168.38928207647604,
                    802.9981915807903,
                    3.7065231800079346
                ]
            ],
            "adjacent_keypoints": []
        }
    ],
    "face_info": [
        {
            "key_points": [
                [
                    984,
                    260
                ],
                [
                    984,
                    274
                ],
                [
                    986,
                    291
                ],
                [
                    988,
                    305
                ],
                [
                    994,
                    317
                ],
                [
                    1004,
                    329
                ],
                [
                    1014,
                    337
                ],
                [
                    1024,
                    344
                ],
                [
                    1034,
                    345
                ],
                [
                    1043,
                    342
                ],
                [
                    1051,
                    334
                ],
                [
                    1059,
                    325
                ],
                [
                    1065,
                    314
                ],
                [
                    1070,
                    302
                ],
                [
                    1072,
                    288
                ],
                [
                    1072,
                    274
                ],
                [
                    1072,
                    261
                ],
                [
                    999,
                    247
                ],
                [
                    1005,
                    244
                ],
                [
                    1012,
                    242
                ],
                [
                    1019,
                    242
                ],
                [
                    1024,
                    245
                ],
                [
                    1037,
                    246
                ],
                [
                    1043,
                    243
                ],
                [
                    1050,
                    243
                ],
                [
                    1057,
                    246
                ],
                [
                    1061,
                    252
                ],
                [
                    1031,
                    259
                ],
                [
                    1031,
                    267
                ],
                [
                    1032,
                    275
                ],
                [
                    1033,
                    283
                ],
                [
                    1024,
                    289
                ],
                [
                    1028,
                    290
                ],
                [
                    1032,
                    292
                ],
                [
                    1036,
                    291
                ],
                [
                    1041,
                    289
                ],
                [
                    1007,
                    260
                ],
                [
                    1011,
                    257
                ],
                [
                    1016,
                    257
                ],
                [
                    1020,
                    262
                ],
                [
                    1016,
                    263
                ],
                [
                    1011,
                    262
                ],
                [
                    1040,
                    262
                ],
                [
                    1044,
                    258
                ],
                [
                    1049,
                    258
                ],
                [
                    1053,
                    261
                ],
                [
                    1049,
                    263
                ],
                [
                    1045,
                    264
                ],
                [
                    1014,
                    306
                ],
                [
                    1021,
                    302
                ],
                [
                    1027,
                    301
                ],
                [
                    1032,
                    302
                ],
                [
                    1036,
                    301
                ],
                [
                    1041,
                    302
                ],
                [
                    1046,
                    306
                ],
                [
                    1041,
                    313
                ],
                [
                    1036,
                    316
                ],
                [
                    1031,
                    317
                ],
                [
                    1026,
                    316
                ],
                [
                    1020,
                    313
                ],
                [
                    1016,
                    305
                ],
                [
                    1027,
                    304
                ],
                [
                    1032,
                    304
                ],
                [
                    1036,
                    304
                ],
                [
                    1044,
                    305
                ],
                [
                    1035,
                    310
                ],
                [
                    1031,
                    311
                ],
                [
                    1026,
                    311
                ]
            ],
            "face_coordinate": [
                973,
                202,
                1079,
                329
            ],
            "expression": "happy",
            "attention_score": 0.815
        }
    ]
}