{
    "image_name": "wushu.mp4/681.jpg",
    "body_info": [
        {
            "box": [
                895,
                65,
                1274,
                1063,
                1
            ],
            "action_cls": "walk",
            "img_action_cls": [
                "climb",
                "other"
            ],
            "keypoints": [
                [
                    188.97728940141877,
                    93.46783393147248,
                    9.98755693435669
                ],
                [
                    209.93569037067857,
                    76.30468561762169,
                    9.969315528869629
                ],
                [
                    168.37220539697785,
                    77.68054264573772,
                    9.980570673942566
                ],
                [
                    230.18026656891675,
                    106.81192527340737,
                    7.521073222160339
                ],
                [
                    136.49311409280875,
                    110.73351093457424,
                    8.654412031173706
                ],
                [
                    270.24384687521916,
                    230.51375571766647,
                    7.810412645339966
                ],
                [
                    96.71324545484248,
                    240.1368080676502,
                    8.949666023254395
                ],
                [
                    307.09596963174295,
                    394.3909297887412,
                    3.951328992843628
                ],
                [
                    53.22200790265711,
                    397.9260899139435,
                    4.648123681545258
                ],
                [
                    315.33041661283187,
                    511.3233742248135,
                    9.329770803451538
                ],
                [
                    64.15886128304128,
                    511.14262092989856,
                    7.996911406517029
                ],
                [
                    244.6385574757568,
                    519.9427795611839,
                    5.855078101158142
                ],
                [
                    142.65498548729954,
                    533.4186855961549,
                    4.013893008232117
                ],
                [
                    237.73636661053993,
                    719.9411667855484,
                    8.045953512191772
                ],
                [
                    142.41793156833182,
                    745.3984703686301,
                    8.254890441894531
                ],
                [
                    171.2587479278647,
                    883.1646340200667,
                    3.6093980073928833
                ]
            ],
            "adjacent_keypoints": [
                [
                    [
                        244,
                        519
                    ],
                    [
                        270,
                        230
                    ]
                ],
                [
                    [
                        307,
                        394
                    ],
                    [
                        270,
                        230
                    ]
                ],
                [
                    [
                        307,
                        394
                    ],
                    [
                        315,
                        511
                    ]
                ],
                [
                    [
                        244,
                        519
                    ],
                    [
                        237,
                        719
                    ]
                ],
                [
                    [
                        142,
                        533
                    ],
                    [
                        96,
                        240
                    ]
                ],
                [
                    [
                        53,
                        397
                    ],
                    [
                        96,
                        240
                    ]
                ],
                [
                    [
                        53,
                        397
                    ],
                    [
                        64,
                        511
                    ]
                ],
                [
                    [
                        142,
                        533
                    ],
                    [
                        142,
                        745
                    ]
                ],
                [
                    [
                        142,
                        745
                    ],
                    [
                        171,
                        883
                    ]
                ],
                [
                    [
                        270,
                        230
                    ],
                    [
                        96,
                        240
                    ]
                ],
                [
                    [
                        244,
                        519
                    ],
                    [
                        142,
                        533
                    ]
                ]
            ]
        }
    ],
    "face_info": [
        {
            "key_points": [
                [
                    1032,
                    147
                ],
                [
                    1032,
                    160
                ],
                [
                    1033,
                    174
                ],
                [
                    1034,
                    187
                ],
                [
                    1038,
                    198
                ],
                [
                    1046,
                    206
                ],
                [
                    1055,
                    212
                ],
                [
                    1066,
                    217
                ],
                [
                    1077,
                    218
                ],
                [
                    1088,
                    218
                ],
                [
                    1099,
                    215
                ],
                [
                    1109,
                    210
                ],
                [
                    1117,
                    202
                ],
                [
                    1122,
                    192
                ],
                [
                    1125,
                    180
                ],
                [
                    1127,
                    168
                ],
                [
                    1128,
                    155
                ],
                [
                    1049,
                    133
                ],
                [
                    1055,
                    126
                ],
                [
                    1063,
                    124
                ],
                [
                    1072,
                    124
                ],
                [
                    1080,
                    128
                ],
                [
                    1090,
                    129
                ],
                [
                    1099,
                    127
                ],
                [
                    1107,
                    127
                ],
                [
                    1115,
                    131
                ],
                [
                    1119,
                    137
                ],
                [
                    1084,
                    139
                ],
                [
                    1084,
                    145
                ],
                [
                    1084,
                    150
                ],
                [
                    1084,
                    157
                ],
                [
                    1074,
                    166
                ],
                [
                    1078,
                    167
                ],
                [
                    1083,
                    168
                ],
                [
                    1088,
                    168
                ],
                [
                    1093,
                    167
                ],
                [
                    1058,
                    141
                ],
                [
                    1062,
                    138
                ],
                [
                    1067,
                    138
                ],
                [
                    1072,
                    142
                ],
                [
                    1067,
                    142
                ],
                [
                    1062,
                    142
                ],
                [
                    1096,
                    143
                ],
                [
                    1101,
                    140
                ],
                [
                    1106,
                    141
                ],
                [
                    1110,
                    144
                ],
                [
                    1106,
                    144
                ],
                [
                    1101,
                    143
                ],
                [
                    1065,
                    186
                ],
                [
                    1073,
                    181
                ],
                [
                    1080,
                    178
                ],
                [
                    1083,
                    179
                ],
                [
                    1087,
                    178
                ],
                [
                    1093,
                    181
                ],
                [
                    1097,
                    188
                ],
                [
                    1092,
                    190
                ],
                [
                    1086,
                    191
                ],
                [
                    1082,
                    191
                ],
                [
                    1078,
                    191
                ],
                [
                    1072,
                    190
                ],
                [
                    1068,
                    186
                ],
                [
                    1079,
                    182
                ],
                [
                    1083,
                    182
                ],
                [
                    1087,
                    182
                ],
                [
                    1095,
                    187
                ],
                [
                    1086,
                    186
                ],
                [
                    1082,
                    186
                ],
                [
                    1079,
                    186
                ]
            ],
            "face_coordinate": [
                1020,
                84,
                1133,
                218
            ],
            "expression": "happy",
            "attention_score": 0.815
        }
    ]
}