{
    "image_name": "wushu.mp4/860.jpg",
    "body_info": [
        {
            "box": [
                862,
                235,
                1158,
                1078,
                1
            ],
            "action_cls": "walk",
            "img_action_cls": [
                "climb",
                "phone"
            ],
            "keypoints": [
                [
                    142.86179919391353,
                    117.42650763670795,
                    9.977078437805176
                ],
                [
                    159.7046948073232,
                    97.19899245899838,
                    9.332045316696167
                ],
                [
                    127.73164206640118,
                    98.17929007540516,
                    9.469869136810303
                ],
                [
                    183.64996444807744,
                    112.2055714460982,
                    7.0387595891952515
                ],
                [
                    193.92904535049385,
                    199.81411518197675,
                    5.5436772108078
                ],
                [
                    87.41486047130967,
                    207.24579864218026,
                    5.158456563949585
                ],
                [
                    24.638452232915224,
                    189.62343270667031,
                    5.345547199249268
                ],
                [
                    174.85607625043926,
                    733.9438443075137,
                    5.01240611076355
                ],
                [
                    101.09760625634638,
                    821.5474431151246,
                    4.474363923072815
                ]
            ],
            "adjacent_keypoints": [
                [
                    [
                        24,
                        189
                    ],
                    [
                        87,
                        207
                    ]
                ],
                [
                    [
                        193,
                        199
                    ],
                    [
                        87,
                        207
                    ]
                ]
            ]
        }
    ],
    "face_info": [
        {
            "key_points": [
                [
                    968,
                    336
                ],
                [
                    969,
                    351
                ],
                [
                    971,
                    364
                ],
                [
                    973,
                    377
                ],
                [
                    977,
                    389
                ],
                [
                    983,
                    397
                ],
                [
                    990,
                    402
                ],
                [
                    998,
                    406
                ],
                [
                    1006,
                    407
                ],
                [
                    1015,
                    405
                ],
                [
                    1023,
                    400
                ],
                [
                    1030,
                    393
                ],
                [
                    1036,
                    384
                ],
                [
                    1039,
                    372
                ],
                [
                    1040,
                    359
                ],
                [
                    1041,
                    345
                ],
                [
                    1041,
                    331
                ],
                [
                    975,
                    324
                ],
                [
                    979,
                    316
                ],
                [
                    985,
                    312
                ],
                [
                    992,
                    312
                ],
                [
                    998,
                    316
                ],
                [
                    1011,
                    316
                ],
                [
                    1017,
                    314
                ],
                [
                    1024,
                    313
                ],
                [
                    1029,
                    317
                ],
                [
                    1033,
                    325
                ],
                [
                    1005,
                    329
                ],
                [
                    1006,
                    337
                ],
                [
                    1006,
                    344
                ],
                [
                    1007,
                    351
                ],
                [
                    998,
                    359
                ],
                [
                    1002,
                    360
                ],
                [
                    1006,
                    362
                ],
                [
                    1011,
                    360
                ],
                [
                    1014,
                    359
                ],
                [
                    983,
                    332
                ],
                [
                    986,
                    328
                ],
                [
                    991,
                    328
                ],
                [
                    994,
                    332
                ],
                [
                    991,
                    333
                ],
                [
                    987,
                    333
                ],
                [
                    1014,
                    334
                ],
                [
                    1018,
                    329
                ],
                [
                    1022,
                    329
                ],
                [
                    1026,
                    333
                ],
                [
                    1023,
                    334
                ],
                [
                    1018,
                    334
                ],
                [
                    991,
                    375
                ],
                [
                    997,
                    370
                ],
                [
                    1002,
                    368
                ],
                [
                    1006,
                    369
                ],
                [
                    1010,
                    368
                ],
                [
                    1015,
                    370
                ],
                [
                    1019,
                    375
                ],
                [
                    1015,
                    380
                ],
                [
                    1010,
                    382
                ],
                [
                    1006,
                    383
                ],
                [
                    1002,
                    382
                ],
                [
                    997,
                    380
                ],
                [
                    993,
                    374
                ],
                [
                    1002,
                    373
                ],
                [
                    1006,
                    374
                ],
                [
                    1010,
                    373
                ],
                [
                    1017,
                    374
                ],
                [
                    1010,
                    376
                ],
                [
                    1006,
                    377
                ],
                [
                    1002,
                    376
                ]
            ],
            "face_coordinate": [
                964,
                282,
                1039,
                410
            ],
            "expression": "amazing",
            "attention_score": 0.855
        }
    ]
}